rocketsolver/models/atmosphere/__init__.py
rocketsolver/models/materials/__init__.py
rocketsolver/models/materials/composites.py
rocketsolver/models/materials/elastics.py
rocketsolver/models/materials/metals.py
rocketsolver/models/materials/plastics.py
rocketsolver/models/propulsion/__init__.py
rocketsolver/models/propulsion/thermals.py
rocketsolver/models/propulsion/grain/__init__.py
rocketsolver/models/propulsion/grain/fmm/_2d.py
rocketsolver/models/propulsion/grain/fmm/_3d.py
rocketsolver/models/propulsion/grain/fmm/__init__.py
rocketsolver/models/propulsion/grain/fmm/stl.py
rocketsolver/models/propulsion/grain/geometries/__init__.py
rocketsolver/models/propulsion/grain/geometries/bates.py
rocketsolver/models/propulsion/grain/geometries/conical.py
rocketsolver/models/propulsion/grain/geometries/d_grain.py
rocketsolver/models/propulsion/grain/geometries/multi_port.py
rocketsolver/models/propulsion/grain/geometries/rod_and_tube.py
rocketsolver/models/propulsion/grain/geometries/star.py
rocketsolver/models/propulsion/grain/geometries/wagon_wheel.py
rocketsolver/models/propulsion/propellants/__init__.py
rocketsolver/models/propulsion/propellants/solid.py
rocketsolver/models/propulsion/structure/__init__.py
rocketsolver/models/propulsion/structure/chamber.py
rocketsolver/models/propulsion/structure/nozzle.py
rocketsolver/models/recovery/__init__.py
rocketsolver/models/recovery/events.py
rocketsolver/models/recovery/parachutes.py
rocketsolver/models/rocket/__init__.py
rocketsolver/models/rocket/fuselage.py
rocketsolver/montecarlo/__init__.py
rocketsolver/montecarlo/random.py
rocketsolver/operations/__init__.py
rocketsolver/operations/ballistics/_1dof.py
rocketsolver/operations/ballistics/__init__.py
rocketsolver/operations/internal_ballistics/__init__.py
rocketsolver/services/conversions.py
rocketsolver/services/decorators.py
rocketsolver/services/equations.py
rocketsolver/services/factories.py
rocketsolver/services/isentropic_flow.py
rocketsolver-0.5.0.dist-info/METADATA
rocketsolver-0.5.0.dist-info/WHEEL
rocketsolver-0.5.0.dist-info/top_level.txt
rocketsolver-0.5.0.dist-info/RECORD
