Metadata-Version: 2.1
Name: rocketsolver
Version: 0.5.0
Summary: Rocket simulator
Author-email: Felipe Bogaerts de Mattos <me@felipebm.com>
License: GNU GENERAL PUBLIC LICENSE
Project-URL: Homepage, https://github.com/felipebogaertsm/rocket-solver
Keywords: python,rocket,srm,engine,propulsion
Classifier: Programming Language :: Python :: 3
Classifier: Operating System :: Unix
Classifier: Operating System :: MacOS :: MacOS X
Classifier: Operating System :: Microsoft :: Windows
Requires-Python: >=3.9
Requires-Dist: numpy
Requires-Dist: pandas
Requires-Dist: fluids
Requires-Dist: matplotlib
Requires-Dist: plotly
Requires-Dist: scipy
Provides-Extra: dev
Requires-Dist: black ; extra == 'dev'
Requires-Dist: pytest ; extra == 'dev'
Requires-Dist: bumpver ; extra == 'dev'
